docx_format_translate/__init__.py
docx_format_translate/docx_translate.py
docx_format_translate/utils.py
docx_format_translate-0.1.1.dist-info/METADATA
docx_format_translate-0.1.1.dist-info/WHEEL
docx_format_translate-0.1.1.dist-info/top_level.txt
docx_format_translate-0.1.1.dist-info/RECORD
