Metadata-Version: 2.4
Name: docx-format-translate
Version: 0.1.1
Summary: Translate docx with format
Author-email: Qianwang Wang <1039094655@qq.com>
License: MIT
Project-URL: Homepage, https://github.com/Chienwang5/docx-translate-format
Classifier: Programming Language :: Python :: 3
Classifier: License :: OSI Approved :: MIT License
